README.rst
setup.py
hitchcli/__init__.py
hitchcli/command_line_steps.py
hitchcli.egg-info/PKG-INFO
hitchcli.egg-info/SOURCES.txt
hitchcli.egg-info/dependency_links.txt
hitchcli.egg-info/not-zip-safe
hitchcli.egg-info/requires.txt
hitchcli.egg-info/top_level.txt